pytest_abq/__init__.py
pytest_abq/version.py
pytest_abq/abq/__init__.py
pytest_abq/abq/config.py
pytest_abq/abq/net.py
pytest_abq/abq/types.py
pytest_abq-1.0.1.dist-info/LICENSE
pytest_abq-1.0.1.dist-info/METADATA
pytest_abq-1.0.1.dist-info/WHEEL
pytest_abq-1.0.1.dist-info/entry_points.txt
pytest_abq-1.0.1.dist-info/top_level.txt
pytest_abq-1.0.1.dist-info/RECORD
