Metadata-Version: 2.1
Name: pytest-abq
Version: 1.0.1
Summary: Pytest integration for the ABQ universal test runner.
License: MIT
Project-URL: Homepage, https://github.com/rwx-research/pytest-abq
Project-URL: Bug Tracker, https://github.com/rwx-research/pytest-abq/issues
Classifier: Programming Language :: Python :: 3
Classifier: License :: OSI Approved :: MIT License
Classifier: Operating System :: OS Independent
Requires-Python: >=3.7
License-File: LICENSE
Requires-Dist: typing-extensions
